{
  "heroData": {
    "bgImgLink": "/images/background/hero-bg.jpg",
    "imgLink": "/images/section/DavitHero.png",
    "title": "Davit",
    "subTitle": "Hello, I’m",
    "designation": "Web Developer 🚀 "
  },
  "aboutData": {
    "imgLink": "/images/section/DavitHero.png",
    "cvPdf": "/images/Davit-Spanderashvili-CV-ENG.pdf",
    "title": "Hi There! I'm Davit Spanderashvili",
    "subtitle": "Web Developer",
    "text": "I am a Web Developer who seeks improvment and focused on discipline with 4 years of experience. I specialize in creating responsive, user-friendly websites and thrive on solving challenges with clean, efficient code. With a passion for continuous learning and a commitment to best practices, I deliver reliable, high-quality solutions. Let’s build something great together!",
    "details": [
      {
        "title": "Birthday",
        "info": "13 Oct, 1997"
      },
      {
        "title": "Phone",
        "info": "+995 558 49 94 00"
      },
      {
        "title": "Email",
        "info": "dspanderashvili@gmail.coms"
      },
      {
        "title": "From",
        "info": "Tbilisi, Georgia"
      },
      {
        "title": "Language",
        "info": "Georgian, English, Russian"
      },
      {
        "title": "Remote",
        "info": "Available"
      },
      {
        "title": "On-Site",
        "info": "Available"
      },
      {
        "title": "Contract",
        "info": "Available"
      },
      {
        "title": "Freelance",
        "info": "Available"
      }
    ]
  },
  "serviceData": {
    "services": [
      {
        "imgLink": "/images/icon/icon1.png",
        "title": "Front-End",
        "text": "I’ll join your team to handle all front-end tasks, delivering a pixel-perfect product that mirrors the design. Using modern practices, I’ll ensure the code is clean, scalable, and ready to grow with your project’s future needs.",
        "effect": "zoom-out-up",
        "duration": "500",
        "delay": "200"
      },
      {
        "imgLink": "/images/icon/icon2.png",
        "title": "UI/UX Collaboration Package ",
        "text": "I’ll work closely with the R&D team and UI/UX designer to develop the best possible design focusing on OG idea, ensuring a seamless and user-centered experience across all platforms.",
        "effect": "zoom-out-up",
        "duration": "500",
        "delay": "300"
      },
      {
        "imgLink": "/images/icon/icon6.png",
        "title": "Responsive Design",
        "text": "I’ll ensure your website looks and functions flawlessly across all devices, using flexible layouts and modern techniques for a seamless experience on desktops, tablets, and smartphones.",
        "effect": "zoom-out-up",
        "duration": "500",
        "delay": "700"
      },
     
      {
        "imgLink": "/images/icon/icon4.png",
        "title": "Contract: Full-Stack and SEO Package",
        "text": "A two-person team will cover both front-end and back-end development, ensuring smooth integration between the UI and server-side. Additionally, we’ll implement SEO optimization to enhance visibility and performance, delivering a complete, efficient, and scalable solution tailored to your project’s needs.",
        "effect": "zoom-out-up",
        "duration": "500",
        "delay": "500"
      },
      {
        "imgLink": "/images/icon/icon5.png",
        "title": "Contract: Web and Mobile Package",
        "text": "I’ll develop cohesive web and mobile applications that provide a seamless and intuitive user experience across all platforms. Utilizing responsive design principles, I ensure that your website and mobile app adapt beautifully to various screen sizes, from desktops to tablets and smartphones.",
        "effect": "zoom-out-up",
        "duration": "500",
        "delay": "600"
      },
       {
        "imgLink": "/images/icon/icon3.png",
        "title": "Contract: Project",
        "text": "Our dedicated team, including front-end and back-end developers, a mobile developer, a project manager, a UI/UX designer, and an SEO specialist, will collaboratively manage every aspect of your project. From initial design to final deployment, we ensure a seamless, high-quality product that meets your goals, enhances visibility, and exceeds expectations.",
        "effect": "zoom-out-up",
        "duration": "500",
        "delay": "400"
      }
    ]
  },
  "skillData": {
    "title": "Dynamic Web Developer: Transforming Ideas into Reality",
    "text": "As an seasoned web developer specializing in React.js and Next.js 🌐, I bring extensive experience in creating dynamic, responsive web applications. My proficiency allows me to craft modern digital solutions that captivate users and deliver seamless experiences 🚀. I’m passionate about optimizing code 🛠️ and discovering efficient practices and design patterns. Committed to high standards, I thrive in collaborative environments that drive results 🤝. I’m excited to join a team that values innovation and excellence — let’s discuss how I can contribute to your projects! 📬",
    "skills": [
      {
        "title": "Markup - HTML5 CSS3 Sass",
        "progress": "Vary Good",
        "effect": "fade-up",
        "duration": "500",
        "delay": "200"
      },
      {
        "title": "JS - EcmaScript6+ Advanced",
        "progress": "Good",
        "effect": "fade-up",
        "duration": "500",
        "delay": "300"
      },
      {
        "title": "React.js and packages",
        "progress": "Good",
        "effect": "fade-up",
        "duration": "500",
        "delay": "400"
      },
      {
        "title": "Next.js & Vercel",
        "progress": "Avarage",
        "effect": "fade-up",
        "duration": "500",
        "delay": "500"
      },
      {
        "title": "SEO - Bots and Meta Tags",
        "progress": "Vary Good",
        "effect": "fade-up",
        "duration": "500",
        "delay": "600"
      },
      {
        "title": "Git/Github",
        "progress": "Good",
        "effect": "fade-up",
        "duration": "500",
        "delay": "700"
      },
      {
        "title": "Wordpress",
        "progress": "Good",
        "effect": "fade-up",
        "duration": "500",
        "delay": "700"
      }
    ]
  },
  "portfolioData": {
    "portfolioItems": [
      {
        "imgLink": "/images/portfolio/portfolio1.jpg",
        "imgLinkLg": "/images/portfolio/portfolio1_lg.jpg",
        "title": "Product Design",
        "subTitle": "Design / Marketing",
        "effect": "fade-up",
        "duration": "500",
        "delay": "200"
      },
      {
        "imgLink": "/images/portfolio/portfolio5.jpg",
        "imgLinkLg": "/images/portfolio/portfolio5_lg.jpg",
        "title": "Product Design",
        "subTitle": "Design / Marketing",
        "effect": "fade-up",
        "duration": "500",
        "delay": "600"
      },
      {
        "imgLink": "/images/portfolio/portfolio5.jpg",
        "imgLinkLg": "/images/portfolio/portfolio5_lg.jpg",
        "title": "Product Design",
        "subTitle": "Design / Marketing",
        "effect": "fade-up",
        "duration": "500",
        "delay": "600"
      }
    ]
  },
  "blogData": {
    "useFor": "blog",
    "sliderSetting": {
      "infinite": true,
      "speed": 500,
      "slidesToShow": 3,
      "slidesToScroll": 1,
      "arrows": false,
      "responsive": [
        {
          "breakpoint": 991,
          "settings": {
            "slidesToShow": 2,
            "autoplay": true
          }
        },
        {
          "breakpoint": 767,
          "settings": {
            "slidesToShow": 1,
            "autoplay": true
          }
        }
      ]
    },
    "informations": [
      
      
      
     
      
    ]
  },
  "reviewData": {
    "useFor": "review",
    "sliderSetting": {
      "infinite": true,
      "speed": 500,
      "slidesToShow": 3,
      "slidesToScroll": 1,
      "arrows": false,
      "responsive": [
        {
          "breakpoint": 991,
          "settings": {
            "slidesToShow": 2,
            "autoplay": true
          }
        },
        {
          "breakpoint": 767,
          "settings": {
            "slidesToShow": 1,
            "autoplay": true
          }
        }
      ]
    },
    "informations": [
      {
        "imgLink": "/images/client/client1.png",
        "title": "Richard Miles",
        "designation": "Chairman",
        "text": "Lorem ipsum dolor sit, amet consectetur adipisicing elit. Ullam accusamus autem itaque blanditiis enim debitis totam facilis reiciendis voluptate aspernatur!"
      },
      {
        "imgLink": "/images/client/client2.png",
        "title": "Vesta Shufelt",
        "designation": "Executive Director",
        "text": "Lorem ipsum dolor sit, amet consectetur adipisicing elit. Ullam accusamus autem itaque blanditiis enim debitis totam facilis reiciendis voluptate aspernatur!"
      },
      {
        "imgLink": "/images/client/client3.png",
        "title": "Joseph Alves",
        "designation": "Managing Director",
        "text": "Lorem ipsum dolor sit, amet consectetur adipisicing elit. Ullam accusamus autem itaque blanditiis enim debitis totam facilis reiciendis voluptate aspernatur!"
      },
      {
        "imgLink": "/images/client/client1.png",
        "title": "Richard Miles",
        "designation": "Chairman",
        "text": "Lorem ipsum dolor sit, amet consectetur adipisicing elit. Ullam accusamus autem itaque blanditiis enim debitis totam facilis reiciendis voluptate aspernatur!"
      },
      {
        "imgLink": "/images/client/client2.png",
        "title": "Vesta Shufelt",
        "designation": "Executive Director",
        "text": "Lorem ipsum dolor sit, amet consectetur adipisicing elit. Ullam accusamus autem itaque blanditiis enim debitis totam facilis reiciendis voluptate aspernatur!"
      },
      {
        "imgLink": "/images/client/client3.png",
        "title": "Joseph Alves",
        "designation": "Managing Director",
        "text": "Lorem ipsum dolor sit, amet consectetur adipisicing elit. Ullam accusamus autem itaque blanditiis enim debitis totam facilis reiciendis voluptate aspernatur!"
      }
    ]
  },
  "resumeData": {
    "experienceTitle": "Experience",
    "experience": [
      {
        "title": "Wordpress",
        "duration": "Jul 2024 - Sept 2024 ( Contract )",
        "subTitle": "Farmway",
        "text": "Lorem ipsum dolor sit amet, consectetur adipiscing elit. Nunc ligula nulla, tincidunt id faucibus sed, suscipit feugiat turpis."
      },
      {
        "title": "Wordpress",
        "duration": "Aug 2023 - Sept 2023 ( Contract )",
        "subTitle": "Wilbour Holding",
        "text": "Lorem ipsum dolor sit amet, consectetur adipiscing elit. Nunc ligula nulla, tincidunt id faucibus sed, suscipit feugiat turpis."
      },
      {
        "title": "Wordpress / React.js",
        "duration": "Mar 2023 - Oct 2023",
        "subTitle": "Nomad Capitalist",
        "text": "Lorem ipsum dolor sit amet, consectetur adipiscing elit. Nunc ligula nulla, tincidunt id faucibus sed, suscipit feugiat turpis."
      },
      {
        "title": "Next.js / React.js / Vercel",
        "duration": "Feb 2022 - Mar 2023",
        "subTitle": "Sweeft Digital | A Making Science Company",
        "text": "Lorem ipsum dolor sit amet, consectetur adipiscing elit. Nunc ligula nulla, tincidunt id faucibus sed, suscipit feugiat turpis."
      },
      {
        "title": "Next.js / React.js / Vercel",
        "duration": "Apr 2022 - Nov 2022",
        "subTitle": "Apart Development",
        "text": "Lorem ipsum dolor sit amet, consectetur adipiscing elit. Nunc ligula nulla, tincidunt id faucibus sed, suscipit feugiat turpis."
      },
      {
        "title": "Wordpress",
        "duration": "Dec 2021 - Jul 2022",
        "subTitle": "Revenue Capital",
        "text": "Lorem ipsum dolor sit amet, consectetur adipiscing elit. Nunc ligula nulla, tincidunt id faucibus sed, suscipit feugiat turpis."
      }
    ],
    "educationTitle": "Education",
    "education": [
      {
        "title": "Master of Computer Science",
        "duration": "2015 - 2016",
        "subTitle": "University of XYZ",
        "text": "Lorem ipsum dolor sit amet, consectetur adipiscing elit. Nunc ligula nulla, tincidunt id faucibus sed, suscipit feugiat turpis."
      },
      {
        "title": "Bachelor of Computer Science",
        "duration": "2010 - 2014",
        "subTitle": "University of ABC",
        "text": "Lorem ipsum dolor sit amet, consectetur adipiscing elit. Nunc ligula nulla, tincidunt id faucibus sed, suscipit feugiat turpis."
      },
      {
        "title": "Diploma in Computer Science",
        "duration": "2006 - 2010",
        "subTitle": "XYZ Institution",
        "text": "Lorem ipsum dolor sit amet, consectetur adipiscing elit. Nunc ligula nulla, tincidunt id faucibus sed, suscipit feugiat turpis."
      }
    ]
  },
  "contactData": {
    "formTitle": "Let's get connected",
    "title": "Contact Info",
    "subTitle": "Visite my social profile and get connected",
    "text": "Thinking about a project or collaboration? Two heads are better then one lets connect 😊"
  },
  "socialData": [
    {
      "icon": "github",
      "title": "Github",
      "link": "https://github.com/davitITguy"
    },
    {
      "icon": "instagram",
      "title": "Instagram",
      "link": "https://www.instagram.com/davit_spanderashvili/"
    },
    
    {
      "icon": "linkedin",
      "title": "LinkedIn",
      "link": "https://www.linkedin.com/in/davit-spanderashvili-b26239173/"
    }
  ]
}
